djangorestframework_kicksaw_auth/__init__.py
djangorestframework_kicksaw_auth/authentication.py
djangorestframework_kicksaw_auth-1.0.0.dist-info/WHEEL
djangorestframework_kicksaw_auth-1.0.0.dist-info/METADATA
djangorestframework_kicksaw_auth-1.0.0.dist-info/RECORD
