Metadata-Version: 2.1
Name: djangorestframework-kicksaw-auth
Version: 1.0.0
Summary: Provides DRF auth classes that are backed by various AWS resources
Home-page: https://github.com/Kicksaw-Consulting/djangorestframework-kicksaw-auth
Keywords: django,djangorestframework,drf,aws,apigateway
Author: Alex Drozd
Author-email: alex@kicksaw.com
Requires-Python: >=3.8,<4.0
Classifier: Programming Language :: Python :: 3
Classifier: Programming Language :: Python :: 3.8
Classifier: Programming Language :: Python :: 3.9
Requires-Dist: boto3 (>=1.17.51,<2.0.0)
Requires-Dist: djangorestframework (>=3.12.4,<4.0.0)
Project-URL: Repository, https://github.com/Kicksaw-Consulting/djangorestframework-kicksaw-auth
